[
    {
        "tuido_dotpha": {
            "7": {
                "so_luong": 15818
            },
            "4": {
                "so_luong": 0
            },
            "5": {
                "so_luong": 0
            }
        },
        "tuido_nguyenlieu": {
            "10": {
                "so_luong": 304
            },
            "14": {
                "so_luong": 648
            },
            "5": {
                "so_luong": 279
            },
            "11": {
                "so_luong": 241
            },
            "8": {
                "so_luong": 192
            },
            "12": {
                "so_luong": 115
            },
            "3": {
                "so_luong": 152
            },
            "15": {
                "so_luong": 109
            }
        },
        "tuido_vannang": {
            "10": {
                "so_luong": 0
            },
            "2": {
                "so_luong": 0,
                "su_dung": 1
            },
            "6": {
                "so_luong": 6
            },
            "7": {
                "so_luong": 24
            },
            "8": {
                "so_luong": 0,
                "su_dung": 95
            },
            "9": {
                "so_luong": 1
            },
            "3": {
                "so_luong": 0
            },
            "4": {
                "so_luong": 0,
                "su_dung": 1
            },
            "14": {
                "so_luong": 0
            }
        },
        "cong_phap": {
            "2": {
                "so_luong": 9
            },
            "1": {
                "so_luong": 50
            },
            "8": {
                "so_luong": 0
            }
        }
    }
]